{
  "products": [
    {
      "id": "prod-mnnz7boc-pchv3y",
      "description": "Used Honor X8 with 128GB storage. Configured with 6+2GB memory. Good condition."
    },
    {
      "id": "prod-mnnylcht-o6llx3",
      "description": "Brand new Samsung A17 4G with official warranty. Contact us for color options. Configured with 4GB RAM and 128GB storage."
    },
    {
      "id": "prod-mnnz7c6q-ztw1ea",
      "description": "Used Honor X9C with 256GB storage. Configured with 12GB RAM. Good condition."
    },
    {
      "id": "prod-mnnz7crj-1msd5r",
      "description": "Used Samsung Galaxy A73 5G with 128GB storage. Configured with 8GB RAM. Good condition."
    },
    {
      "id": "prod-mnnz7elc-iwnhq1",
      "description": "Used Nokia C20 with 32GB storage. Good condition."
    },
    {
      "id": "prod-mnnz7dy1-88bplj",
      "description": "Used Tecno Spark Go 1 with 64GB storage. Configured with 3GB RAM. Good condition."
    },
    {
      "id": "prod-mnnylbrz-gnvfvh",
      "description": "Brand new Samsung A36 5G with official warranty. Contact us for color options. Configured with 6GB RAM and 128GB storage."
    },
    {
      "id": "prod-mnnyld0a-ejxqds",
      "description": "Brand new Samsung A06 4G with official warranty. Contact us for color options. Configured with 4GB RAM and 64GB storage."
    },
    {
      "id": "prod-mnnylbbb-y7nfct",
      "description": "Brand new Samsung A56 5G with official warranty. Contact us for color options. Configured with 8GB RAM and 128GB storage."
    },
    {
      "id": "prod-mnnz7dcf-h2lui0",
      "description": "Used Redmi Note 8 with 128GB storage. Configured with 6GB RAM. Good condition."
    }
  ]
}
